odoo/addons/l10n_it_fatturapa_in/README.rst
odoo/addons/l10n_it_fatturapa_in/__init__.py
odoo/addons/l10n_it_fatturapa_in/__manifest__.py
odoo/addons/l10n_it_fatturapa_in/fields.py
odoo/addons/l10n_it_fatturapa_in/i18n/de.po
odoo/addons/l10n_it_fatturapa_in/i18n/it.po
odoo/addons/l10n_it_fatturapa_in/i18n/l10n_it_fatturapa_in.pot
odoo/addons/l10n_it_fatturapa_in/migrations/13.0.1.0.0/noupdate_changes.xml
odoo/addons/l10n_it_fatturapa_in/migrations/13.0.1.0.0/post-migration.py
odoo/addons/l10n_it_fatturapa_in/migrations/13.0.1.0.0/pre-migration.py
odoo/addons/l10n_it_fatturapa_in/migrations/14.0.2.3.0/post-migrate.py
odoo/addons/l10n_it_fatturapa_in/models/__init__.py
odoo/addons/l10n_it_fatturapa_in/models/account.py
odoo/addons/l10n_it_fatturapa_in/models/attachment.py
odoo/addons/l10n_it_fatturapa_in/models/company.py
odoo/addons/l10n_it_fatturapa_in/models/partner.py
odoo/addons/l10n_it_fatturapa_in/readme/CONFIGURE.rst
odoo/addons/l10n_it_fatturapa_in/readme/CONTRIBUTORS.rst
odoo/addons/l10n_it_fatturapa_in/readme/DESCRIPTION.rst
odoo/addons/l10n_it_fatturapa_in/readme/INSTALL.rst
odoo/addons/l10n_it_fatturapa_in/readme/ROADMAP.rst
odoo/addons/l10n_it_fatturapa_in/readme/USAGE.rst
odoo/addons/l10n_it_fatturapa_in/security/ir.model.access.csv
odoo/addons/l10n_it_fatturapa_in/security/rules.xml
odoo/addons/l10n_it_fatturapa_in/static/description/icon.png
odoo/addons/l10n_it_fatturapa_in/static/description/index.html
odoo/addons/l10n_it_fatturapa_in/static/src/img/icon.png
odoo/addons/l10n_it_fatturapa_in/tests/__init__.py
odoo/addons/l10n_it_fatturapa_in/tests/fatturapa_common.py
odoo/addons/l10n_it_fatturapa_in/tests/test_fix_bad_uris.py
odoo/addons/l10n_it_fatturapa_in/tests/test_import_fatturapa_xml.py
odoo/addons/l10n_it_fatturapa_in/tests/data/IT01234567890_FPR03.base64.xml.p7m
odoo/addons/l10n_it_fatturapa_in/tests/data/IT01234567890_FPR03.xml
odoo/addons/l10n_it_fatturapa_in/tests/data/IT01234567890_FPR03.xml.p7m
odoo14_addon_l10n_it_fatturapa_in-14.0.2.4.3.dist-info/METADATA
odoo14_addon_l10n_it_fatturapa_in-14.0.2.4.3.dist-info/WHEEL
odoo14_addon_l10n_it_fatturapa_in-14.0.2.4.3.dist-info/top_level.txt
odoo14_addon_l10n_it_fatturapa_in-14.0.2.4.3.dist-info/RECORD
