Metadata-Version: 2.1
Name: odoo14-addon-l10n_it_fatturapa_in
Version: 14.0.2.4.3
Summary: Ricezione fatture elettroniche
Home-page: https://github.com/OCA/l10n-italy
Author: Agile Business Group, Innoviu, Odoo Community Association (OCA)
Author-email: support@odoo-community.org
License: AGPL-3
Classifier: Programming Language :: Python
Classifier: Framework :: Odoo
Classifier: Framework :: Odoo :: 14.0
Classifier: License :: OSI Approved :: GNU Affero General Public License v3
Classifier: Development Status :: 4 - Beta
Requires-Python: >=3.6
Requires-Dist: asn1crypto
Requires-Dist: elementpath
Requires-Dist: odoo14-addon-l10n-it-fatturapa
Requires-Dist: odoo14-addon-l10n-it-fiscal-document-type
Requires-Dist: odoo14-addon-l10n-it-withholding-tax-reason
Requires-Dist: odoo<14.1dev,>=14.0a
